{"pl_cbflag":"0","pl_disc":"2005","pl_pelink":"http://exoplanet.eu/catalog/hd_109749_b/","st_rad":"1.24","pl_imgflag":"0","pl_facility":"W. M. Keck Observatory","st_teff":"5903.00","pl_astflag":"0","hip_name":"HIP 61595 A","pl_pnum":"1","st_optmag":"8.208","ra":"189.318237","pl_discmethod":"Radial Velocity","st_age":"3.700","hd_name":"HD 109749","pl_hostname":"HD 109749","st_mass":"1.20","pl_tranflag":"0","pl_name":"HD 109749 b","pl_rvflag":"1","pl_orbeccen":"0.010000","rowupdate":"2014-05-14","st_dist":"59.03","pl_telescope":"10 m Keck I Telescope","pl_edelink":"http://exoplanets.org/detail/HD_109749_b","pl_omflag":"0","pl_orbper":"5.24000000","dec":"-40.812115"}