{"pl_cbflag":"0","pl_disc":"2009","pl_pelink":"http://exoplanet.eu/catalog/corot-7_c/","st_rad":"0.82","pl_imgflag":"0","pl_massj":"0.02643","pl_masse":"8.40000","pl_facility":"CoRoT","st_teff":"5259.00","pl_astflag":"0","pl_pnum":"2","st_optmag":"11.668","ra":"100.956125","pl_discmethod":"Radial Velocity","st_age":"1.320","pl_hostname":"CoRoT-7","st_mass":"0.91","pl_tranflag":"0","pl_name":"CoRoT-7 c","pl_rvflag":"1","pl_orbeccen":"0.000000","rowupdate":"2015-09-10","st_dist":"153.70","pl_telescope":"0.27 m CoRoT Telescope","pl_omflag":"0","pl_orbper":"3.69800000","dec":"-1.063033"}