{"pl_cbflag":"0","pl_disc":"2009","pl_pelink":"http://exoplanet.eu/catalog/gj_1214_b/","st_rad":"0.18","pl_imgflag":"0","pl_massj":"0.01970","pl_masse":"6.26125","pl_facility":"MEarth Project","st_teff":"3170.00","pl_dens":"1.49000","pl_astflag":"0","pl_pnum":"1","st_optmag":"15.100","ra":"258.828837","pl_discmethod":"Transit","pl_hostname":"GJ 1214","st_mass":"0.16","pl_tranflag":"1","pl_rade":"2.847","pl_radj":"0.254","pl_name":"GJ 1214 b","pl_rvflag":"1","pl_ratdor":"14.000000","rowupdate":"2015-12-03","pl_telescope":"0.4 m MEarth Telescope","pl_edelink":"http://exoplanets.org/detail/GJ_1214_b","pl_omflag":"0","pl_orbper":"1.58040456","dec":"4.963920"}