{"pl_disc":"14 Her","pl_pelink":"0","st_rad":"1","pl_massj":"0","st_dist":"14 Her b","st_teff":"0.369000","null":["","18.15","0.90","6.610","","5311.00","http://exoplanet.eu/catalog/14_her_b/","http://exoplanets.org/detail/14_Her_b"],"pl_dens":"2002","pl_eqt":"Radial Velocity","st_optmag":"0","ra":"1","pl_discmethod":"0","pl_hostname":"43.817646","st_mass":"1773.40000000","pl_rade":"HIP 79248","pl_radj":"0","pl_name":"HD 145675","rowupdate":"2014-05-14","pl_facility":"W. M. Keck Observatory","pl_edelink":"242.601303","dec":"10 m Keck I Telescope"}