{"pl_cbflag":"0","pl_disc":"2014","pl_pelink":"http://exoplanet.eu/catalog/kepler-123_b/","st_rad":"1.26","pl_imgflag":"0","pl_facility":"Kepler","st_teff":"6089.00","pl_astflag":"0","pl_pnum":"2","st_optmag":"14.061","ra":"296.998621","pl_discmethod":"Transit","pl_hostname":"Kepler-123","st_mass":"1.03","pl_tranflag":"1","pl_rade":"2.940","pl_radj":"0.262","pl_name":"Kepler-123 b","pl_rvflag":"0","rowupdate":"2014-05-14","pl_telescope":"0.95 m Kepler Telescope","pl_edelink":"http://exoplanets.org/detail/Kepler-123_b","pl_omflag":"0","pl_orbper":"17.23236600","dec":"42.781956"}