{"pl_cbflag":"0","pl_disc":"2014","st_rad":"1.02","pl_imgflag":"0","pl_massj":"0.02700","pl_masse":"8.46000","pl_facility":"Kepler","st_teff":"5690.00","pl_dens":"2.26000","pl_astflag":"0","pl_pnum":"1","st_optmag":"10.297","ra":"297.069643","pl_discmethod":"Transit","st_age":"2.340","pl_hostname":"Kepler-96","st_mass":"1.00","pl_tranflag":"1","pl_rade":"2.670","pl_radj":"0.238","pl_name":"Kepler-96 b","pl_rvflag":"1","rowupdate":"2014-05-14","pl_telescope":"0.95 m Kepler Telescope","pl_omflag":"0","pl_orbper":"16.23850000","dec":"40.525141"}